disbots/__init__.py
disbots-1.0.1.dist-info/LICENSE.txt
disbots-1.0.1.dist-info/METADATA
disbots-1.0.1.dist-info/WHEEL
disbots-1.0.1.dist-info/top_level.txt
disbots-1.0.1.dist-info/RECORD
