Metadata-Version: 2.1
Name: disbots
Version: 1.0.1
Summary: A library made for disbots.xyz
Home-page: UNKNOWN
Author: RoyalDj9730322
License: UNKNOWN
Platform: UNKNOWN
Classifier: Programming Language :: Python :: 3
Classifier: License :: OSI Approved :: MIT License
Classifier: Operating System :: OS Independent
Requires-Python: >=3.6
License-File: LICENSE.txt
Requires-Dist: aiohttp
